jwtools/__init__.py
jwtools/dt.py
jwtools/func.py
jwtools/io_util.py
jwtools/tests/__init__.py
jwtools/tests/test_base.py
jwtools/tests/feature/__init__.py
jwtools/tests/script/__init__.py
jwtools/tests/script/test1.py
jwtools/tests/script/test2.py
jwtools/tests/unit/__init__.py
jwtools/tests/unit/dt_test.py
jwtools/tests/unit/func_test.py
jwtools/tests/unit/io_test.py
jwtools-0.1.19.dist-info/LICENSE
jwtools-0.1.19.dist-info/METADATA
jwtools-0.1.19.dist-info/WHEEL
jwtools-0.1.19.dist-info/top_level.txt
jwtools-0.1.19.dist-info/RECORD
