Metadata-Version: 2.1
Name: jwtools
Version: 0.1.19
Summary: It is a micro-toolbox that includes various common operations and will continue to be improved in the future.
Home-page: https://gitee.com/jiwei-data/python-jwtools.git
Author: jinghewang
Author-email: jinghewang@163.com
License: MIT License
Classifier: Programming Language :: Python :: 3
Classifier: License :: OSI Approved :: MIT License
Classifier: Operating System :: OS Independent
Requires-Python: >=3.9
License-File: LICENSE
